odoo10_addon_medical_pathology-10.0.1.0.0-py2.7-nspkg.pth
odoo/addons/medical_pathology/README.rst
odoo/addons/medical_pathology/__init__.py
odoo/addons/medical_pathology/__manifest__.py
odoo/addons/medical_pathology/data/medical_pathology_code_type.xml
odoo/addons/medical_pathology/demo/medical_pathology_category_demo.xml
odoo/addons/medical_pathology/demo/medical_pathology_demo.xml
odoo/addons/medical_pathology/i18n/es_CO.po
odoo/addons/medical_pathology/i18n/pt_BR.po
odoo/addons/medical_pathology/models/__init__.py
odoo/addons/medical_pathology/models/medical_pathology.py
odoo/addons/medical_pathology/models/medical_pathology_category.py
odoo/addons/medical_pathology/models/medical_pathology_code_type.py
odoo/addons/medical_pathology/security/ir.model.access.csv
odoo/addons/medical_pathology/static/description/icon.png
odoo/addons/medical_pathology/static/description/screenshot_pathologies.png
odoo/addons/medical_pathology/static/description/screenshot_pathology_categories.png
odoo/addons/medical_pathology/tests/__init__.py
odoo/addons/medical_pathology/tests/test_medical_pathology.py
odoo/addons/medical_pathology/tests/test_medical_pathology_category.py
odoo/addons/medical_pathology/views/medical_menu.xml
odoo/addons/medical_pathology/views/medical_pathology_category_view.xml
odoo/addons/medical_pathology/views/medical_pathology_view.xml
odoo10_addon_medical_pathology-10.0.1.0.0.dist-info/DESCRIPTION.rst
odoo10_addon_medical_pathology-10.0.1.0.0.dist-info/METADATA
odoo10_addon_medical_pathology-10.0.1.0.0.dist-info/RECORD
odoo10_addon_medical_pathology-10.0.1.0.0.dist-info/WHEEL
odoo10_addon_medical_pathology-10.0.1.0.0.dist-info/metadata.json
odoo10_addon_medical_pathology-10.0.1.0.0.dist-info/namespace_packages.txt
odoo10_addon_medical_pathology-10.0.1.0.0.dist-info/top_level.txt
